{"type":"byte","validValues":[],"settingMethods":["ActivateMapAnims","BattleIntro","CallInSafeGFXMode","ClearTilemapEtc","CrystalIntro","EnableMobile","FindFirstAliveMonAndStartBattle","FlyFunction","Function11ac51","HallOfFame_FadeOutMusic","InitBattleDisplay","LoadMapGraphics","NamingScreen","NewGame_ClearTilemapEtc","NewPokedexEntry","PhoneRing_CopyTilemapAtOnce","Pokedex","RedCredits","RunMobileTradeAnim_Frontpics","RunMobileTradeAnim_NoFrontpics","RunTradeAnimScript","SaveMenu_CopyTilemapAtOnce","SetRAMStateForMobile","StatsScreenInit_gotaddress","SuspendMapAnims","TilesetColorTest","_ComposeMailMessage","_DepositPKMN","_MovePKMNWithoutMail","_WithdrawPKMN"],"usingMethods":["CallInSafeGFXMode","NamingScreen","NewPokedexEntry","PhoneRing_CopyTilemapAtOnce","RunMobileTradeAnim_Frontpics","RunMobileTradeAnim_NoFrontpics","RunTradeAnimScript","SaveMenu_CopyTilemapAtOnce","StatsScreenInit_gotaddress","_ComposeMailMessage"],"name":"hMapAnims","file":"hram.asm","lineNo":147,"address":58927,"addressUsedBy":[]}