{"type":"byte","validValues":[],"settingMethods":[],"usingMethods":[],"name":"wPartyMon1Item","lineNo":2,"address":29219,"addressUsedBy":["DoNPCTrade","GiveShuckle","IsMonHoldingEverstone","ApplyCleanseTagEffectOnEncounterRate","DayCareAskDepositPokemon","Unused_GetPartyMenuMonIcon","HandleBerserkGene","GivePokeMail","ConsumeHeldItem","CheckPokeMail","BillsPC_LoadMonStats","PartyMenu_InitAnimatedMonIcon","MoveMailFromPCToParty","CheckTimeCapsuleCompatibility","Function_PartyItemsAreUnique","IsAnyMonHoldingMail","GetPartymonItem","Function17ded9","GivePoke"]}