{"type":"byte","validValues":[],"settingMethods":["EnterMapConnection","EnterMapSpawnPoint"],"usingMethods":["CheckForHiddenItems","CheckObjectEnteringVisibleRange","Function437b","Function56a3","GetMapScreenCoords","InitializeVisibleSprites","IsObjectMovingOffEdgeOfScreen","PlayerSpawn_ConvertCoords","RefreshPlayerCoords","SnorlaxAwake"],"name":"wXCoord","file":"wram.asm","lineNo":2901,"address":29215,"addressUsedBy":["UpdatePlayerCoords","FollowNotExact","CopyTempObjectToObjectStruct","EnterMapConnection"]}