{"names":["_LoadStandardFont"],"callingMethods":[],"methodsCalled":["Copy1bpp","Get1bppViaHDMA"],"methodAddressesUsed":[],"varsSet":[],"varsUsed":["rLCDC"],"varAddressesUsed":["vTiles1"],"constantsUsed":["LEN_1BPP_TILE","tile"],"lines":["_LoadStandardFont::","\tld de, Font","\tld hl, vTiles1","\tlb bc, BANK(Font), 128 ; \"A\" to \"9\"","\tldh a, [rLCDC]","\tbit rLCDC_ENABLE, a","\tjp z, Copy1bpp","","\tld de, Font","\tld hl, vTiles1","\tlb bc, BANK(Font), 32 ; \"A\" to \"]\"","\tcall Get1bppViaHDMA","\tld de, Font + 32 * LEN_1BPP_TILE","\tld hl, vTiles1 tile $20","\tlb bc, BANK(Font), 32 ; \"a\" to $bf","\tcall Get1bppViaHDMA","\tld de, Font + 64 * LEN_1BPP_TILE","\tld hl, vTiles1 tile $40","\tlb bc, BANK(Font), 32 ; \"Ä\" to \"←\"","\tcall Get1bppViaHDMA","\tld de, Font + 96 * LEN_1BPP_TILE","\tld hl, vTiles1 tile $60","\tlb bc, BANK(Font), 32 ; \"\u0027\" to \"9\"","\tcall Get1bppViaHDMA","\tret"],"name":"_LoadStandardFont","file":"engine/gfx/load_font.asm","lineNo":18,"address":251540,"addressUsedBy":[]}