{"names":["AICheckLastPlayerMon"],"callingMethods":["AI_Smart_Curse","AI_Smart_MeanLook","AI_Smart_Selfdestruct"],"methodsCalled":[],"methodAddressesUsed":[],"varsSet":[],"varsUsed":["wCurBattleMon","wPartyCount"],"varAddressesUsed":["wPartyMon1HP"],"constantsUsed":["PARTYMON_STRUCT_LENGTH"],"lines":["AICheckLastPlayerMon:","\tld a, [wPartyCount]","\tld b, a","\tld c, 0","\tld hl, wPartyMon1HP","\tld de, PARTYMON_STRUCT_LENGTH","",".loop","\tld a, [wCurBattleMon]","\tcp c","\tjr z, .skip","","\tld a, [hli]","\tor [hl]","\tret nz","\tdec hl","",".skip","\tadd hl, de","\tinc c","\tdec b","\tjr nz, .loop","","\tret"],"name":"AICheckLastPlayerMon","file":"engine/battle/ai/scoring.asm","lineNo":1774,"address":126532,"addressUsedBy":[]}