{"names":["AIGetEnemyMove"],"callingMethods":["AIHasMoveEffect","AI_Aggressive","AI_Basic","AI_Offensive","AI_Risky","AI_Setup","AI_Smart","AI_Smart_Counter","AI_Smart_Encore","AI_Smart_LockOn","AI_Smart_Mimic","AI_Smart_MirrorCoat","AI_Smart_RazorWind","AI_Smart_Unused2B","AI_Status","AI_Types"],"methodsCalled":["AddNTimes","FarCopyBytes"],"methodAddressesUsed":[],"varsSet":[],"varsUsed":[],"varAddressesUsed":["Moves"],"constantsUsed":["MOVE_LENGTH"],"lines":["AIGetEnemyMove:","; Load attributes of move a into ram","","\tpush hl","\tpush de","\tpush bc","\tdec a","\tld hl, Moves","\tld bc, MOVE_LENGTH","\tcall AddNTimes","","\tld de, wEnemyMoveStruct","\tld a, BANK(Moves)","\tcall FarCopyBytes","","\tpop bc","\tpop de","\tpop hl","\tret"],"name":"AIGetEnemyMove","file":"engine/battle/ai/scoring.asm","lineNo":3216,"address":127585,"addressUsedBy":[]}