{"names":["BattleCommand_DefrostOpponent"],"callingMethods":[],"methodsCalled":["AnimateCurrentMove","BattleCommand_StatUp","Defrost","GetBattleVarAddr"],"methodAddressesUsed":[],"varsSet":[],"varsUsed":[],"varAddressesUsed":[],"constantsUsed":["BATTLE_VARS_MOVE_EFFECT","BATTLE_VARS_STATUS_OPP","EFFECT_ATTACK_UP"],"lines":["BattleCommand_DefrostOpponent:","; defrostopponent","; Thaw the opponent if frozen, and","; raise the user\u0027s Attack one stage.","","\tcall AnimateCurrentMove","","\tld a, BATTLE_VARS_STATUS_OPP","\tcall GetBattleVarAddr","\tcall Defrost","","\tld a, BATTLE_VARS_MOVE_EFFECT","\tcall GetBattleVarAddr","\tld a, [hl]","\tpush hl","\tpush af","","\tld a, EFFECT_ATTACK_UP","\tld [hl], a","\tcall BattleCommand_StatUp","","\tpop af","\tpop hl","\tld [hl], a","\tret"],"name":"BattleCommand_DefrostOpponent","file":"engine/battle/effect_commands.asm","lineNo":3346,"address":119901,"addressUsedBy":[]}