{"names":["BattleAnimCmd_Transform"],"callingMethods":[],"methodsCalled":["Predef"],"methodAddressesUsed":[],"varsSet":["rSVBK","wCurPartySpecies"],"varsUsed":["hBattleTurn","rSVBK","wCurPartySpecies","wTempBattleMonSpecies","wTempEnemyMonSpecies"],"varAddressesUsed":["GetMonBackpicPredef","GetMonFrontpicPredef","GetUnownLetterPredef","vTiles0","wBattleMonDVs","wCurPartySpecies","wEnemyMonDVs"],"constantsUsed":["tile"],"lines":["BattleAnimCmd_Transform:","\tldh a, [rSVBK]","\tpush af","\tld a, BANK(wCurPartySpecies)","\tldh [rSVBK], a","","\tld a, [wCurPartySpecies]","\tpush af","","\tldh a, [hBattleTurn]","\tand a","\tjr z, .player","","\tld a, [wTempBattleMonSpecies]","\tld [wCurPartySpecies], a","\tld hl, wBattleMonDVs","\tpredef GetUnownLetter","\tld de, vTiles0 tile $00","\tpredef GetMonFrontpic","\tjr .done","",".player","\tld a, [wTempEnemyMonSpecies]","\tld [wCurPartySpecies], a","\tld hl, wEnemyMonDVs","\tpredef GetUnownLetter","\tld de, vTiles0 tile $00","\tpredef GetMonBackpic","",".done","\tpop af","\tld [wCurPartySpecies], a","","\tpop af","\tldh [rSVBK], a","\tret"],"name":"BattleAnimCmd_Transform","file":"engine/battle_anims/anim_commands.asm","lineNo":890,"address":224276,"addressUsedBy":[]}