{"names":["BattleTowerAction_GetChallengeState"],"callingMethods":[],"methodsCalled":["CloseSRAM","OpenSRAM"],"methodAddressesUsed":[],"varsSet":["wScriptVar"],"varsUsed":[],"varAddressesUsed":["sBattleTowerChallengeState"],"constantsUsed":[],"lines":["BattleTowerAction_GetChallengeState:","\tld hl, sBattleTowerChallengeState","\tld a, BANK(sBattleTowerChallengeState)","\tcall OpenSRAM","\tld a, [hl]","\tld [wScriptVar], a","\tcall CloseSRAM","\tret"],"name":"BattleTowerAction_GetChallengeState","file":"engine/events/battle_tower/battle_tower.asm","lineNo":1018,"address":294685,"addressUsedBy":[]}