{"names":["BattleBGEffects_ResetVideoHRAM"],"callingMethods":["BGEffect_RapidCyclePals","BattleBGEffect_1c","BattleBGEffect_2a"],"methodsCalled":["BattleBGEffects_ClearLYOverrides"],"methodAddressesUsed":[],"varsSet":["hLCDCPointer","hLYOverrideEnd","hLYOverrideStart","rBGP","wBGP","wOBP1"],"varsUsed":[],"varAddressesUsed":[],"constantsUsed":[],"lines":["BattleBGEffects_ResetVideoHRAM:","\txor a","\tldh [hLCDCPointer], a","\tld a, %11100100","\tldh [rBGP], a","\tld [wBGP], a","\tld [wOBP1], a","\tldh [hLYOverrideStart], a","\tldh [hLYOverrideEnd], a","\tcall BattleBGEffects_ClearLYOverrides","\tret"],"name":"BattleBGEffects_ResetVideoHRAM","file":"engine/battle_anims/bg_effects.asm","lineNo":2665,"address":211819,"addressUsedBy":[]}