{"names":["CheckCutCollision"],"callingMethods":[],"methodsCalled":["IsInArray"],"methodAddressesUsed":[],"varsSet":[],"varsUsed":[],"varAddressesUsed":[],"constantsUsed":[],"lines":["CheckCutCollision:","\tld a, c","\tld hl, .blocks","\tld de, 1","\tcall IsInArray","\tret","",".blocks","\tdb COLL_CUT_TREE","\tdb COLL_CUT_TREE_1A","\tdb COLL_TALL_GRASS_10","\tdb COLL_TALL_GRASS","\tdb COLL_LONG_GRASS","\tdb COLL_LONG_GRASS_1C","\tdb -1"],"name":"CheckCutCollision","file":"engine/overworld/tile_events.asm","lineNo":76,"address":90829,"addressUsedBy":["CheckMapForSomethingToCut"]}