{"names":["DepositBreedmon"],"callingMethods":["DepositMonWithDayCareLady","DepositMonWithDayCareMan"],"methodsCalled":["AddNTimes","CopyBytes","SkipNames"],"methodAddressesUsed":[],"varsSet":[],"varsUsed":["wCurPartyMon"],"varAddressesUsed":["wPartyMon1Species","wPartyMonNicknames","wPartyMonOT"],"constantsUsed":["BOXMON_STRUCT_LENGTH","PARTYMON_STRUCT_LENGTH"],"lines":["DepositBreedmon:","\tld a, [wCurPartyMon]","\tld hl, wPartyMonNicknames","\tcall SkipNames","\tcall CopyBytes","\tld a, [wCurPartyMon]","\tld hl, wPartyMonOT","\tcall SkipNames","\tcall CopyBytes","\tld a, [wCurPartyMon]","\tld hl, wPartyMon1Species","\tld bc, PARTYMON_STRUCT_LENGTH","\tcall AddNTimes","\tld bc, BOXMON_STRUCT_LENGTH","\tjp CopyBytes"],"name":"DepositBreedmon","file":"engine/pokemon/move_mon.asm","lineNo":925,"address":77636,"addressUsedBy":[]}