{"names":["DummyGame_InitStrings"],"callingMethods":["_DummyGame"],"methodsCalled":["ByteFill","PlaceString","PrintText"],"methodAddressesUsed":[],"varsSet":[],"varsUsed":[],"varAddressesUsed":[],"constantsUsed":["SCREEN_HEIGHT","SCREEN_WIDTH"],"lines":["DummyGame_InitStrings:","\thlcoord 0, 0","\tld bc, SCREEN_WIDTH * SCREEN_HEIGHT","\tld a, $1","\tcall ByteFill","\thlcoord 0, 0","\tld de, .japstr1","\tcall PlaceString","\thlcoord 15, 0","\tld de, .japstr2","\tcall PlaceString","\tld hl, .dummy_text","\tcall PrintText","\tret","",".dummy_text","\tdb \"@\"",".japstr1","\tdb \"とったもの@\"",".japstr2","\tdb \"あと　かい@\""],"name":"DummyGame_InitStrings","file":"engine/games/dummy_game.asm","lineNo":448,"address":245596,"addressUsedBy":[]}