{"names":["FieldMoveFailed"],"callingMethods":["FlashFunction","FlyFunction","Jumptable_cdae","TryHeadbuttFromMenu","TryRockSmashFromMenu","WaterfallFunction"],"methodsCalled":["MenuTextboxBackup"],"methodAddressesUsed":[],"varsSet":[],"varsUsed":[],"varAddressesUsed":[],"constantsUsed":[],"lines":["FieldMoveFailed:","\tld hl, .CantUseItemText","\tcall MenuTextboxBackup","\tret","",".CantUseItemText:","\ttext_far _CantUseItemText","\ttext_end"],"name":"FieldMoveFailed","file":"engine/events/overworld.asm","lineNo":108,"address":74143,"addressUsedBy":[]}