{"names":["Function81bde"],"callingMethods":["Function81bc0"],"methodsCalled":["ByteFill"],"methodAddressesUsed":[],"varsSet":[],"varsUsed":[],"varAddressesUsed":[],"constantsUsed":["DEBUGTEST_TICKS_1","DEBUGTEST_TICKS_2"],"lines":["Function81bde:","\tpush af","\tld a, DEBUGTEST_TICKS_1","\tld [hli], a","\tld bc, $f","\tld a, DEBUGTEST_TICKS_2","\tcall ByteFill","\tld l, e","\tld h, d","\tpop af","\tld bc, $28","\tcall ByteFill","\tret"],"name":"Function81bde","file":"engine/menus/debug.asm","lineNo":393,"address":172228,"addressUsedBy":[]}