{"names":["Function1082db"],"callingMethods":["MobileTradeAnim_GetOddEgg","MobileTradeAnim_ShowOTMonFromGTS","MobileTradeAnim_ShowOTMonFromTrade"],"methodsCalled":["FarCall"],"methodAddressesUsed":["HDMATransferTilemapToWRAMBank3","PlaySpriteAnimations","SetUpPokeAnim"],"varsSet":[],"varsUsed":[],"varAddressesUsed":[],"constantsUsed":[],"lines":["\tfarcall PlaySpriteAnimations","\tfarcall SetUpPokeAnim","\tfarcall HDMATransferTilemapToWRAMBank3","\tjr nc, .loop","\tret"],"name":"Function1082db","lineNo":1,"address":265756,"addressUsedBy":[]}