{"names":["Function116758"],"callingMethods":["Function1162f2"],"methodsCalled":[],"methodAddressesUsed":[],"varsSet":["wc314"],"varsUsed":["wc30f"],"varAddressesUsed":[],"constantsUsed":[],"lines":["Function116758:","\tld a, [wc30f]","\tcp $30","\tjr c, .asm_116770","\tjr z, .asm_116770","\tcp $38","\tjr c, .asm_116774","\tjr z, .asm_116774","\tcp $40","\tjr c, .asm_116778","\tjr z, .asm_116778","\txor a","\tjr .asm_11677a","",".asm_116770","\tld a, $c","\tjr .asm_11677a","",".asm_116774","\tld a, $8","\tjr .asm_11677a","",".asm_116778","\tld a, $4","",".asm_11677a","\tld [wc314 + 4], a","\tret"],"name":"Function116758","file":"mobile/mobile_45_2.asm","lineNo":306,"address":274098,"addressUsedBy":[]}