{"names":["Function114243"],"callingMethods":[],"methodsCalled":[],"methodAddressesUsed":[],"varsSet":["MBC3SRamEnable"],"varsUsed":["hSRAMBank"],"varAddressesUsed":["Jumptable_114165"],"constantsUsed":["SRAM_ENABLE"],"lines":["Function114243::","\tld a, SRAM_ENABLE","\tld [MBC3SRamEnable], a","\tldh a, [hSRAMBank]","\tpush af ; if [$dc02] \u003d\u003d 0, this is popped to pc.","\tpush de","\tld a, [$dc02]","\tadd a","\tld e, a","\tld d, 0","\tld hl, Jumptable_114165","\tadd hl, de","\tld a, [hli]","\tld h, [hl]","\tld l, a","\tpop de","\tjp hl"],"name":"Function114243","file":"mobile/mobile_45.asm","lineNo":127,"address":268794,"addressUsedBy":[]}