{"names":["Function28ade"],"callingMethods":["Function28ac9","LinkTradePartymonMenuLoop"],"methodsCalled":["FarCall","JoyTextDelay","LinkTrade_OTPartyMenu","LinkTrade_PlayerPartyMenu"],"methodAddressesUsed":["Function16d6ce"],"fallsInto":"Function28b22","varsSet":["SCREEN_WIDTH","wMenuCursorY","wPlayerLinkAction"],"varsUsed":["hJoyLast","wOTPartyCount","wOtherPlayerLinkMode"],"varAddressesUsed":[],"constantsUsed":["wTilemap"],"lines":["Function28ade:",".loop1","\tld a, \"▶\"","\tldcoord_a 9, 17",".loop2","\tcall JoyTextDelay","\tldh a, [hJoyLast]","\tand a","\tjr z, .loop2","\tbit A_BUTTON_F, a","\tjr nz, .a_button","\tpush af","\tld a, \" \"","\tldcoord_a 9, 17","\tpop af","\tbit D_UP_F, a","\tjr z, .d_up","\tld a, [wOTPartyCount]","\tld [wMenuCursorY], a","\tjp LinkTrade_OTPartyMenu","",".d_up","\tld a, $1","\tld [wMenuCursorY], a","\tjp LinkTrade_PlayerPartyMenu","",".a_button","\tld a, \"▷\"","\tldcoord_a 9, 17","\tld a, $f","\tld [wPlayerLinkAction], a","\tfarcall Function16d6ce","\tld a, [wOtherPlayerLinkMode]","\tcp $f","\tjr nz, .loop1","Function28b22:"],"name":"Function28ade","file":"engine/link/link.asm","lineNo":1512,"address":103727,"addressUsedBy":[]}