{"names":["Function11b7e5"],"callingMethods":[],"methodsCalled":["CloseSRAM","CloseSubmenu","CopyBytes","FadeToMenu","FarCall","GetMapSceneID","OpenSRAM","RestartMapMusic","SpeechTextbox"],"methodAddressesUsed":["EvolvePokemon","Function17d1f1","GetCaughtGender","MobileTradeAnimation_ReceiveGetmonFromGTS","SaveAfterLinkTrade"],"varsSet":["wCurPartySpecies","wForceEvolution","wLinkMode","wOTTrademonCaughtData","wOTTrademonDVs","wOTTrademonID","wOTTrademonSpecies","wc74e"],"varsUsed":["MON_ID","wMapGroup","wMapNumber","wcd81"],"varAddressesUsed":["wOTTrademonOTName"],"constantsUsed":["LINK_TRADECENTER","MON_DVS"],"lines":["Function11b7e5:","\tld a, [$c60d] ; species","\tld [wOTTrademonSpecies], a","\tld [wCurPartySpecies], a","\tld a, [wcd81]","\tld [wc74e], a","\tld hl, $c63d ; OT","\tld de, wOTTrademonOTName","\tld bc, 5","\tcall CopyBytes","\tld a, \"@\"","\tld [de], a","\tld a, [$c60d + MON_ID] ; id","\tld [wOTTrademonID], a","\tld a, [$c60d + MON_ID + 1]","\tld [wOTTrademonID + 1], a","\tld hl, $c60d + MON_DVS ; dvs","\tld a, [hli]","\tld [wOTTrademonDVs], a","\tld a, [hl]","\tld [wOTTrademonDVs + 1], a","\tld bc, $c60d ; pokemon_data_start","\tfarcall GetCaughtGender","\tld a, c","\tld [wOTTrademonCaughtData], a","\tcall SpeechTextbox","\tcall FadeToMenu","\tfarcall MobileTradeAnimation_ReceiveGetmonFromGTS","\tfarcall Function17d1f1","\tld a, $1","\tld [wForceEvolution], a","\tld a, LINK_TRADECENTER","\tld [wLinkMode], a","\tfarcall EvolvePokemon","\txor a","\tld [wLinkMode], a","\tfarcall SaveAfterLinkTrade","\tld a, $5","\tcall OpenSRAM","\tld a, $5","\tld [$a800], a","\tcall CloseSRAM","\tld a, [wMapGroup]","\tld b, a","\tld a, [wMapNumber]","\tld c, a","\tcall GetMapSceneID","\tld a, d","\tor e","\tjr z, .asm_11b872","\tld a, $1","\tld [de], a","",".asm_11b872","\tcall CloseSubmenu","\tcall RestartMapMusic","\tret"],"name":"Function11b7e5","file":"mobile/mobile_46.asm","lineNo":7312,"address":283457,"addressUsedBy":[]}