{"names":["Function1024cb"],"callingMethods":["Function1024c0"],"methodsCalled":[],"methodAddressesUsed":[],"fallsInto":"Function1024de","varsSet":["wcd4a","wcd4e"],"varsUsed":["wcd4a","wcd4f"],"varAddressesUsed":["wcd4e"],"constantsUsed":[],"lines":["Function1024cb:","\tld hl, wcd4e","\tdec [hl]","\tret nz","\tld a, [wcd4f]","\tinc a","\tld [wcd4e], a","\tld a, [wcd4a]","\tinc a","\tld [wcd4a], a","","Function1024de:"],"name":"Function1024cb","file":"mobile/mobile_40.asm","lineNo":5220,"address":259616,"addressUsedBy":[]}