{"names":["Functionce406"],"callingMethods":["BattleAnimFunction_3B"],"methodsCalled":[],"methodAddressesUsed":[],"varsSet":[],"varsUsed":[],"varAddressesUsed":[],"constantsUsed":["BATTLEANIMSTRUCT_PARAM","BATTLEANIMSTRUCT_XCOORD"],"lines":["Functionce406:","\tld hl, BATTLEANIMSTRUCT_PARAM","\tadd hl, bc","\tld a, [hl]","\tld hl, BATTLEANIMSTRUCT_XCOORD","\tadd hl, bc","\tadd [hl]","\tld [hl], a","\tret"],"name":"Functionce406","file":"engine/battle_anims/functions.asm","lineNo":3533,"address":229300,"addressUsedBy":[]}