{"names":["Function1190ec"],"callingMethods":[],"methodsCalled":["BattleTowerRoomMenu_IncrementJumptable","BattleTowerRoomMenu_SetMessage","CloseSRAM","CopyBytes","Function119192","OpenSRAM"],"methodAddressesUsed":[],"varsSet":["rSVBK","s5_aa72"],"varsUsed":["w3_d000","w6_d000","wcd89"],"varAddressesUsed":["s5_aa72","s5_aa73","w6_d000","wBGMapBuffer","wd002"],"constantsUsed":[],"lines":["Function1190ec:","\tld a, BANK(s5_aa73)","\tcall OpenSRAM","\tld hl, wBGMapBuffer","\tld de, s5_aa73","\tld bc, 12","\tcall CopyBytes","\tcall CloseSRAM","\tld a, BANK(s5_aa72)","\tcall OpenSRAM","\tld a, $1","\tld [s5_aa72], a","\tcall CloseSRAM","\tld a, BANK(s6_a000)","\tcall OpenSRAM","\tld a, [w3_d000]","\tld c, a","\tld a, [w3_d000 + 1]","\tld b, a","\tld hl, wd002","\tld de, s6_a000","\tcall Function119192","\tret c","\tld a, [wcd89]","\tand $1","\tjr z, .asm_11913e","\tld a, BANK(w6_d000)","\tldh [rSVBK], a","\tld a, [w6_d000]","\tld c, a","\tld a, [w6_d000 + 1]","\tld b, a","\tld hl, w6_d000 + 2","\tcall Function119192","\tret c","",".asm_11913e","\tld a, BANK(\"Battle Tower RAM\")","\tldh [rSVBK], a","\tcall CloseSRAM","\tld hl, Text_ReceivedNews","\tcall BattleTowerRoomMenu_SetMessage","\tjp BattleTowerRoomMenu_IncrementJumptable"],"name":"Function1190ec","file":"mobile/mobile_46.asm","lineNo":2013,"address":278546,"addressUsedBy":[]}