{"names":["Function104da9"],"callingMethods":["Function104da9","Function104dfe","Function104e46","Function104faf"],"methodsCalled":["Function104da9"],"methodAddressesUsed":[],"varsSet":["rIF"],"varsUsed":[],"varAddressesUsed":[],"constantsUsed":[],"lines":["Function104da9:","\tinc d","\tret z","\txor a","\tldh [rIF], a","\thalt","\tldh a, [c]","\tbit 1, a","\tjr z, Function104da9","\tor a","\tret"],"name":"Function104da9","file":"engine/link/mystery_gift.asm","lineNo":654,"address":263450,"addressUsedBy":[]}