{"names":["Function89464"],"callingMethods":["Function893cc"],"methodsCalled":["FarCopyBytes"],"methodAddressesUsed":[],"varsSet":[],"varsUsed":[],"varAddressesUsed":["vTiles2"],"constantsUsed":["tile","tiles"],"lines":["Function89464:","\tld hl, MobileCardGFX","\tld de, vTiles2","\tld bc, $20 tiles","\tld a, BANK(MobileCardGFX)","\tcall FarCopyBytes","\tld hl, MobileCard2GFX","\tld de, vTiles2 tile $20","\tld bc, $17 tiles","\tld a, BANK(MobileCard2GFX)","\tcall FarCopyBytes","\tret"],"name":"Function89464","file":"mobile/mobile_22.asm","lineNo":554,"address":175991,"addressUsedBy":[]}