{"names":["Function1150b3"],"callingMethods":["Function115062"],"methodsCalled":["Function1158c2"],"methodAddressesUsed":[],"varsSet":["wDecoConsole","wDecoLeftOrnament"],"varsUsed":["wDecoConsole","wDecoLeftOrnament"],"varAddressesUsed":["String_114232","wPartyMon5Defense"],"constantsUsed":[],"lines":["Function1150b3:","\tld hl, $dc24","\tld de, wPartyMon5Defense","\tld b, $0",".asm_1150bb","\tld c, $0","\tld a, [hli]","\tcp $1b","\tjr z, .asm_1150c9","\tld [de], a","\tinc de","\tand a","\tjr z, .asm_115133","\tjr .asm_1150bb","",".asm_1150c9","\tinc c","\tld a, [hl]","\tcp $24","\tjr nz, .asm_1150bb","\tinc hl","\tinc c","\tld a, [hl]","\tcp $42","\tjr z, .asm_1150dc","\tcp $40","\tjr z, .asm_1150dc","\tjr .asm_1150bb","",".asm_1150dc","\tpush hl",".asm_1150dd","\tinc c","\tld a, [hli]","\tand a","\tjr z, .asm_115133","\tcp $1b","\tjr nz, .asm_1150dd","\tinc c","\tld a, [hli]","\tcp $28","\tjr nz, .asm_1150dd","\tinc c","\tld a, [hli]","\tcp $42","\tjr z, .asm_1150f8","\tcp $4a","\tjr z, .asm_1150f8","\tjr .asm_1150dd","",".asm_1150f8","\tld a, l","\tld [wDecoConsole], a","\tld a, h","\tld [wDecoLeftOrnament], a","\tld hl, String_114232",".asm_115103","\tld a, [hli]","\tand a","\tjr z, .asm_11510b","\tld [de], a","\tinc de","\tjr .asm_115103","",".asm_11510b","\tpop hl","\tdec hl","\tdec hl","\tpush de","\tcall Function1158c2","\tpop de","\tld h, d","\tld l, e","\tld c, [hl]","\tinc hl","\tld b, [hl]","\tinc hl",".asm_115119","\tld a, [hli]","\tld [de], a","\tinc de","\tdec bc","\tld a, b","\tor c","\tjr nz, .asm_115119","\tld a, $3f","\tld [de], a","\tinc de","\tld a, $3d","\tld [de], a","\tinc de","\tld a, [wDecoConsole]","\tld l, a","\tld a, [wDecoLeftOrnament]","\tld h, a","\tjr .asm_1150bb","",".asm_115133","\txor a","\tld [de], a","\tret"],"name":"Function1150b3","file":"mobile/mobile_45.asm","lineNo":2784,"address":270989,"addressUsedBy":[]}