{"names":["Function8919e"],"callingMethods":["Function8a1b0","Function8a453"],"methodsCalled":[],"methodAddressesUsed":[],"varsSet":[],"varsUsed":[],"varAddressesUsed":[],"constantsUsed":[],"lines":["Function8919e:","; Searches for the c\u0027th string starting at de.  Returns the pointer in de.","\tld a, c","\tand a","\tret z",".loop","\tld a, [de]","\tinc de","\tcp \"@\"","\tjr nz, .loop","\tdec c","\tjr nz, .loop","\tret"],"name":"Function8919e","file":"mobile/mobile_22.asm","lineNo":79,"address":175627,"addressUsedBy":[]}