{"names":["Functioncd913"],"callingMethods":["Functioncd907"],"methodsCalled":["BattleAnim_Cosine","BattleAnim_Sine","DeinitBattleAnimation"],"methodAddressesUsed":[],"varsSet":[],"varsUsed":[],"varAddressesUsed":[],"constantsUsed":["BATTLEANIMSTRUCT_0F","BATTLEANIMSTRUCT_10","BATTLEANIMSTRUCT_PARAM","BATTLEANIMSTRUCT_XOFFSET","BATTLEANIMSTRUCT_YOFFSET"],"lines":["Functioncd913:","\tld hl, BATTLEANIMSTRUCT_PARAM","\tadd hl, bc","\tld a, [hl]","\tld hl, BATTLEANIMSTRUCT_0F","\tadd hl, bc","\tld d, [hl]","\tpush af","\tpush de","\tcall BattleAnim_Sine","\tld hl, BATTLEANIMSTRUCT_YOFFSET","\tadd hl, bc","\tld [hl], a","\tpop de","\tpop af","\tcall BattleAnim_Cosine","\tld hl, BATTLEANIMSTRUCT_XOFFSET","\tadd hl, bc","\tld [hl], a","\tld hl, BATTLEANIMSTRUCT_0F","\tadd hl, bc","\tld a, [hl]","\tand a","\tjr z, .asm_cd950","\tld d, a","\tld hl, BATTLEANIMSTRUCT_10","\tadd hl, bc","\tld e, [hl]","\tld hl, -$80","\tadd hl, de","\tld e, l","\tld d, h","\tld hl, BATTLEANIMSTRUCT_10","\tadd hl, bc","\tld [hl], e","\tld hl, BATTLEANIMSTRUCT_0F","\tadd hl, bc","\tld [hl], d","\tret","",".asm_cd950","\tcall DeinitBattleAnimation","\tret"],"name":"Functioncd913","file":"engine/battle_anims/functions.asm","lineNo":1596,"address":227623,"addressUsedBy":[]}