{"names":["Function119192"],"callingMethods":["Function119054","Function1190ec","Function119413"],"methodsCalled":["SetMobileErrorCode"],"methodAddressesUsed":[],"varsSet":[],"varsUsed":[],"varAddressesUsed":[],"constantsUsed":[],"lines":["Function119192:","\tinc b","\tinc c","\tjr .asm_11919e","",".asm_119196","\tld a, [hli]","\tld [de], a","\tinc de","\tld a, $bf","\tcp d","\tjr c, .asm_1191a6","",".asm_11919e","\tdec c","\tjr nz, .asm_119196","\tdec b","\tjr nz, .asm_119196","\tand a","\tret","",".asm_1191a6","\tld a, $d3","\tcall SetMobileErrorCode","\tscf","\tret"],"name":"Function119192","file":"mobile/mobile_46.asm","lineNo":2097,"address":278617,"addressUsedBy":[]}