{"names":["GetCardPic"],"callingMethods":[],"methodsCalled":["FarCopyBytes"],"methodAddressesUsed":[],"varsSet":[],"varsUsed":["wPlayerGender"],"varAddressesUsed":["vTiles2"],"constantsUsed":["tile","tiles"],"lines":["GetCardPic:","\tld hl, ChrisCardPic","\tld a, [wPlayerGender]","\tbit PLAYERGENDER_FEMALE_F, a","\tjr z, .GotClass","\tld hl, KrisCardPic",".GotClass:","\tld de, vTiles2 tile $00","\tld bc, $23 tiles","\tld a, BANK(ChrisCardPic) ; aka BANK(KrisCardPic)","\tcall FarCopyBytes","\tld hl, CardGFX","\tld de, vTiles2 tile $23","\tld bc, 6 tiles","\tld a, BANK(CardGFX)","\tcall FarCopyBytes","\tret"],"name":"GetCardPic","file":"engine/gfx/player_gfx.asm","lineNo":105,"address":175459,"addressUsedBy":["TrainerCard"]}