{"names":["GetMartDialogGroup"],"callingMethods":["LoadBuyMenuText","MartAskPurchaseQuantity"],"methodsCalled":[],"methodAddressesUsed":[],"varsSet":[],"varsUsed":["wMartType"],"varAddressesUsed":[],"constantsUsed":[],"lines":["GetMartDialogGroup:","\tld a, [wMartType]","\tld e, a","\tld d, 0","\tld hl, .MartTextFunctionPointers","\tadd hl, de","\tadd hl, de","\tadd hl, de","\tret","",".MartTextFunctionPointers:","\tdwb .StandardMartPointers, 0","\tdwb .HerbShopPointers, 0","\tdwb .BargainShopPointers, 1","\tdwb .PharmacyPointers, 0","\tdwb .StandardMartPointers, 2","",".StandardMartPointers:","\tdw MartHowManyText","\tdw MartFinalPriceText","\tdw MartNoMoneyText","\tdw MartPackFullText","\tdw MartThanksText","\tdw BuyMenuLoop","",".HerbShopPointers:","\tdw HerbalLadyHowManyText","\tdw HerbalLadyFinalPriceText","\tdw HerbalLadyNoMoneyText","\tdw HerbalLadyPackFullText","\tdw HerbalLadyThanksText","\tdw BuyMenuLoop","",".BargainShopPointers:","\tdw BuyMenuLoop","\tdw BargainShopFinalPriceText","\tdw BargainShopNoFundsText","\tdw BargainShopPackFullText","\tdw BargainShopThanksText","\tdw BargainShopSoldOutText","",".PharmacyPointers:","\tdw PharmacyHowManyText","\tdw PharmacyFinalPriceText","\tdw PharmacyNoMoneyText","\tdw PharmacyPackFullText","\tdw PharmacyThanksText","\tdw BuyMenuLoop"],"name":"GetMartDialogGroup","file":"engine/items/mart.asm","lineNo":380,"address":93446,"addressUsedBy":[]}