{"names":["GetPredefPointer"],"callingMethods":[],"methodsCalled":[],"methodAddressesUsed":[],"varsSet":["wPredefAddress","wPredefTemp"],"varsUsed":["wPredefID"],"varAddressesUsed":[],"constantsUsed":[],"lines":["GetPredefPointer::","; Return the bank and address of wPredefID in a and wPredefAddress.","","; Save hl for later (back in Predef)","\tld a, h","\tld [wPredefTemp], a","\tld a, l","\tld [wPredefTemp + 1], a","","\tpush de","\tld a, [wPredefID]","\tld e, a","\tld d, 0","\tld hl, PredefPointers","\tadd hl, de","\tadd hl, de","\tadd hl, de","\tpop de","","\tld a, [hli]","\tld [wPredefAddress + 1], a","\tld a, [hli]","\tld [wPredefAddress], a","\tld a, [hl]","","\tret","","; Predef routines can be used with the \"predef\" and \"predef_jump\" macros.","; This preserves registers bc, de, hl and f."],"name":"GetPredefPointer","file":"engine/predef.asm","lineNo":1,"address":67190,"addressUsedBy":[]}