{"names":["GetStepVector"],"callingMethods":["AddStepVector","GetNextTile","UpdateJumpPosition"],"methodsCalled":[],"methodAddressesUsed":[],"varsSet":[],"varsUsed":[],"varAddressesUsed":["StepVectors"],"constantsUsed":["OBJECT_DIRECTION_WALKING"],"lines":["GetStepVector:","; Return (x, y, duration, speed) in (d, e, a, h).","\tld hl, OBJECT_DIRECTION_WALKING","\tadd hl, bc","\tld a, [hl]","\tand %00001111","\tadd a","\tadd a","\tld l, a","\tld h, 0","\tld de, StepVectors","\tadd hl, de","\tld d, [hl]","\tinc hl","\tld e, [hl]","\tinc hl","\tld a, [hli]","\tld h, [hl]","\tret"],"name":"GetStepVector","file":"engine/overworld/map_objects.asm","lineNo":342,"address":59959,"addressUsedBy":[]}