{"names":["GetTradeAttribute"],"callingMethods":["CheckTradeGender","DoNPCTrade","GetTradeMonNames","NPCTrade","Trade_GetDialog"],"methodsCalled":[],"methodAddressesUsed":[],"varsSet":[],"varsUsed":["wJumptableIndex"],"varAddressesUsed":["NPCTrades"],"constantsUsed":[],"lines":["GetTradeAttribute:","\tld d, 0","\tpush de","\tld a, [wJumptableIndex]","\tand $f","\tswap a","\tld e, a","\tld d, 0","\tld hl, NPCTrades","\tadd hl, de","\tadd hl, de","\tpop de","\tadd hl, de","\tret"],"name":"GetTradeAttribute","file":"engine/events/npc_trade.asm","lineNo":274,"address":254205,"addressUsedBy":[]}