{"names":["GSIntro_GetMonFrontpic"],"callingMethods":[],"methodsCalled":["AddNTimes","FarDecompress","FixPicBank","GetFarByte","GetFarHalfword"],"methodAddressesUsed":[],"varsSet":[],"varsUsed":[],"varAddressesUsed":[],"constantsUsed":[],"lines":["GSIntro_GetMonFrontpic: ; unreferenced","\tld a, c","\tpush de","\tld hl, PokemonPicPointers","\tdec a","\tld bc, 6","\tcall AddNTimes","\tld a, BANK(PokemonPicPointers)","\tcall GetFarByte","\tcall FixPicBank","\tpush af","\tinc hl","\tld a, BANK(PokemonPicPointers)","\tcall GetFarHalfword","\tpop af","\tpop de","\tcall FarDecompress","\tret"],"name":"GSIntro_GetMonFrontpic","file":"engine/gfx/load_pics.asm","lineNo":290,"address":162707,"addressUsedBy":[]}