{"names":["MG_Mobile_Layout00"],"callingMethods":["Function4a492"],"methodsCalled":["FarCall","MG_Mobile_Layout_CreatePalBoxes","MG_Mobile_Layout_LoadPals","MG_Mobile_Layout_WipeAttrmap"],"methodAddressesUsed":["ApplyAttrmap","ApplyPals"],"varsSet":[],"varsUsed":[],"varAddressesUsed":[],"constantsUsed":[],"lines":["MG_Mobile_Layout00:","\tcall MG_Mobile_Layout_LoadPals","\tcall MG_Mobile_Layout_WipeAttrmap","\tcall MG_Mobile_Layout_CreatePalBoxes","\tfarcall ApplyAttrmap","\tfarcall ApplyPals","\tret"],"name":"MG_Mobile_Layout00","file":"engine/gfx/crystal_layouts.asm","lineNo":65,"address":151186,"addressUsedBy":[]}