{"names":["Pokedex_UpdateDexEntryScreen"],"callingMethods":[],"methodsCalled":["MaxVolume","Pokedex_IncrementDexPointer","Pokedex_LoadPointer","Pokedex_MoveArrowCursor","Pokedex_NextOrPreviousDexEntry"],"methodAddressesUsed":["DexEntryScreen_MenuActionJumptable"],"varsSet":["wJumptableIndex","wLastVolume"],"varsUsed":["wDexArrowCursorPosIndex","wLastVolume","wPrevDexEntryJumptableIndex"],"varAddressesUsed":["DexEntryScreen_ArrowCursorData","hJoyPressed"],"constantsUsed":[],"lines":["Pokedex_UpdateDexEntryScreen:","\tld de, DexEntryScreen_ArrowCursorData","\tcall Pokedex_MoveArrowCursor","\tld hl, hJoyPressed","\tld a, [hl]","\tand B_BUTTON","\tjr nz, .return_to_prev_screen","\tld a, [hl]","\tand A_BUTTON","\tjr nz, .do_menu_action","\tcall Pokedex_NextOrPreviousDexEntry","\tret nc","\tcall Pokedex_IncrementDexPointer","\tret","",".do_menu_action","\tld a, [wDexArrowCursorPosIndex]","\tld hl, DexEntryScreen_MenuActionJumptable","\tcall Pokedex_LoadPointer","\tjp hl","",".return_to_prev_screen","\tld a, [wLastVolume]","\tand a","\tjr z, .max_volume","\tld a, $77","\tld [wLastVolume], a","",".max_volume","\tcall MaxVolume","\tld a, [wPrevDexEntryJumptableIndex]","\tld [wJumptableIndex], a","\tret"],"name":"Pokedex_UpdateDexEntryScreen","file":"engine/pokedex/pokedex.asm","lineNo":352,"address":142388,"addressUsedBy":[]}