{"names":["PokeDollEffect"],"callingMethods":[],"methodsCalled":["UseItemText"],"methodAddressesUsed":[],"varsSet":["wBattleResult","wForcedSwitch","wItemEffectSucceeded"],"varsUsed":["wBattleMode","wBattleResult"],"varAddressesUsed":[],"constantsUsed":[],"lines":["PokeDollEffect:","\tld a, [wBattleMode]","\tdec a ; WILD_BATTLE?","\tjr nz, .not_wild","\tinc a ; TRUE","\tld [wForcedSwitch], a","\tld a, [wBattleResult]","\tand BATTLERESULT_BITMASK","\tor DRAW","\tld [wBattleResult], a","\tjp UseItemText","",".not_wild","\txor a","\tld [wItemEffectSucceeded], a","\tret"],"name":"PokeDollEffect","file":"engine/items/item_effects.asm","lineNo":2098,"address":80892,"addressUsedBy":[]}