{"names":["RestorePPEffect"],"callingMethods":[],"methodsCalled":["ApplyPPUp","CopyName1","Elixer_RestorePPofAllMoves","FarCall","GetMoveName","GetMthMoveOfNthPartymon","Not_PP_Up","PPRestoreItem_Cancel","Play_SFX_FULL_HEAL","PrintText","UseItem_SelectMon"],"methodAddressesUsed":["MoveSelectionScreen"],"fallsInto":"FinishPPRestore","varsSet":["wCurMoveNum","wMoveSelectionMenuType","wNamedObjectIndexBuffer","wUsePPUp","wd002"],"varsUsed":["wCurItem","wCurMoveNum","wd002"],"varAddressesUsed":["PPIsMaxedOutText","PPsIncreasedText","RaiseThePPOfWhichMoveText","RestoreThePPOfWhichMoveText","wPartyMon1Moves"],"constantsUsed":["MON_MOVES","MON_PP","PARTYMENUACTION_HEALING_ITEM","PARTYMON_STRUCT_LENGTH","TRUE"],"lines":["RestorePPEffect:","\tld a, [wCurItem]","\tld [wd002], a","",".loop","\t; Party Screen opens to choose on which mon to use the Item","\tld b, PARTYMENUACTION_HEALING_ITEM","\tcall UseItem_SelectMon","\tjp c, PPRestoreItem_Cancel","",".loop2","\tld a, [wd002]","\tcp MAX_ELIXER","\tjp z, Elixer_RestorePPofAllMoves","\tcp ELIXER","\tjp z, Elixer_RestorePPofAllMoves","","\tld hl, RaiseThePPOfWhichMoveText","\tld a, [wd002]","\tcp PP_UP","\tjr z, .ppup","\tld hl, RestoreThePPOfWhichMoveText","",".ppup","\tcall PrintText","","\tld a, [wCurMoveNum]","\tpush af","\txor a","\tld [wCurMoveNum], a","\tld a, $2","\tld [wMoveSelectionMenuType], a","\tfarcall MoveSelectionScreen","\tpop bc","","\tld a, b","\tld [wCurMoveNum], a","\tjr nz, .loop","\tld hl, wPartyMon1Moves","\tld bc, PARTYMON_STRUCT_LENGTH","\tcall GetMthMoveOfNthPartymon","","\tpush hl","\tld a, [hl]","\tld [wNamedObjectIndexBuffer], a","\tcall GetMoveName","\tcall CopyName1","\tpop hl","","\tld a, [wd002]","\tcp PP_UP","\tjp nz, Not_PP_Up","","\tld a, [hl]","\tcp SKETCH","\tjr z, .CantUsePPUpOnSketch","","\tld bc, MON_PP - MON_MOVES","\tadd hl, bc","\tld a, [hl]","\tcp PP_UP_MASK","\tjr c, .do_ppup","",".CantUsePPUpOnSketch:",".pp_is_maxed_out","\tld hl, PPIsMaxedOutText","\tcall PrintText","\tjr .loop2","",".do_ppup","\tld a, [hl]","\tadd PP_UP_ONE","\tld [hl], a","\tld a, TRUE","\tld [wUsePPUp], a","\tcall ApplyPPUp","\tcall Play_SFX_FULL_HEAL","","\tld hl, PPsIncreasedText","\tcall PrintText","","FinishPPRestore:"],"name":"RestorePPEffect","file":"engine/items/item_effects.asm","lineNo":2288,"address":81049,"addressUsedBy":[]}