{"names":["StartTrainerBattle_SineWave"],"callingMethods":[],"methodsCalled":["StartTrainerBattle_DrawSineWave"],"methodAddressesUsed":[],"varsSet":["wJumptableIndex"],"varsUsed":["wcf64"],"varAddressesUsed":["wLYOverrides","wLYOverridesEnd","wcf64","wcf65"],"constantsUsed":["BATTLETRANSITION_FINISH"],"lines":["StartTrainerBattle_SineWave:","\tld a, [wcf64]","\tcp $60","\tjr nc, .end","\tcall .DoSineWave","\tret","",".end","\tld a, BATTLETRANSITION_FINISH","\tld [wJumptableIndex], a","\tret","",".DoSineWave:","\tld hl, wcf65","\tld a, [hl]","\tinc [hl]","\tld hl, wcf64","\tld d, [hl]","\tadd [hl]","\tld [hl], a","\tld a, wLYOverridesEnd - wLYOverrides","\tld bc, wLYOverrides","\tld e, 0","",".loop","\tpush af","\tpush de","\tld a, e","\tcall StartTrainerBattle_DrawSineWave","\tld [bc], a","\tinc bc","\tpop de","\tld a, e","\tadd 2","\tld e, a","\tpop af","\tdec a","\tjr nz, .loop","\tret"],"name":"StartTrainerBattle_SineWave","file":"engine/battle/battle_transition.asm","lineNo":329,"address":181816,"addressUsedBy":[]}