{"names":["TradeAnim_ShowGetmonFrontpic"],"callingMethods":["TradeAnim_ShowGetmonData"],"methodsCalled":[],"methodAddressesUsed":[],"fallsInto":"TradeAnim_ShowFrontpic","varsSet":[],"varsUsed":[],"varAddressesUsed":["vTiles0"],"constantsUsed":["tile"],"lines":["TradeAnim_ShowGetmonFrontpic:","\tld de, vTiles0 tile $31","TradeAnim_ShowFrontpic:"],"name":"TradeAnim_ShowGetmonFrontpic","file":"engine/movie/trade_animation.asm","lineNo":835,"address":104951,"addressUsedBy":["AnimateTrademonFrontpic"]}