{"names":["UnownPuzzle_UpdateTilemap"],"callingMethods":["_UnownPuzzle"],"methodsCalled":["FillUnoccupiedPuzzleSpace","PlaceUnownPuzzlePieceGFX","UnownPuzzle_CheckCurrentTileOccupancy"],"methodAddressesUsed":[],"varsSet":["wUnownPuzzleCursorPosition","wUnownPuzzleHeldPiece"],"varsUsed":[],"varAddressesUsed":["wUnownPuzzleCursorPosition"],"constantsUsed":[],"lines":["UnownPuzzle_UpdateTilemap:","\txor a","\tld [wUnownPuzzleCursorPosition], a","\tld c, 6 * 6",".loop","\tpush bc","\tcall UnownPuzzle_CheckCurrentTileOccupancy","\tld [wUnownPuzzleHeldPiece], a","\tand a","\tjr z, .not_holding_piece","\tcall PlaceUnownPuzzlePieceGFX","\tjr .next","",".not_holding_piece","\tcall FillUnoccupiedPuzzleSpace","",".next","\tld hl, wUnownPuzzleCursorPosition","\tinc [hl]","\tpop bc","\tdec c","\tjr nz, .loop","\tret"],"name":"UnownPuzzle_UpdateTilemap","file":"engine/games/unown_puzzle.asm","lineNo":369,"address":244730,"addressUsedBy":[]}